application/__init__.py
application/core/__init__.py
application/core/parser_data.py
application/core/db/__init__.py
application/core/db/create_db_table.py
application/core/jobs/__init__.py
application/core/jobs/get_masked_or_deleted_db.py
test/__init__.py
test/app.py
my_masker-0.1.2.dist-info/METADATA
my_masker-0.1.2.dist-info/WHEEL
my_masker-0.1.2.dist-info/entry_points.txt
my_masker-0.1.2.dist-info/top_level.txt
my_masker-0.1.2.dist-info/RECORD
