Metadata-Version: 2.1
Name: my-masker
Version: 0.1.2
Summary: UNKNOWN
Home-page: UNKNOWN
License: UNKNOWN
Platform: UNKNOWN
Requires-Dist: SQLAlchemy (~=2.0.22)
Requires-Dist: Flask (~=3.0.0)
